CHANGELOG
COPYRIGHT
INSTALL
LICENSE
MANIFEST.in
README
setup.py
correos/__init__.py
correos/__init__.pyc
correos/api.py
correos/api.pyc
correos/picking.py
correos/picking.pyc
correos/utils.py
correos/utils.pyc
correos.egg-info/PKG-INFO
correos.egg-info/SOURCES.txt
correos.egg-info/dependency_links.txt
correos.egg-info/requires.txt
correos.egg-info/top_level.txt
correos/template/oficinas.xml
correos/template/picking_label.xml
correos/template/picking_send.xml
correos/template/test_connection.xml